{
  "stats": {
    "suites": 8,
    "tests": 89,
    "passes": 70,
    "pending": 0,
    "failures": 11,
    "start": "2025-09-24T17:33:20.075Z",
    "end": "2025-09-24T18:06:11.323Z",
    "duration": 1764999,
    "testsRegistered": 89,
    "passPercent": 78.65168539325843,
    "pendingPercent": 0,
    "other": 0,
    "hasOther": false,
    "skipped": 8,
    "hasSkipped": true
  },
  "results": [
    {
      "uuid": "3dab2d0c-0abb-4454-9d44-622fc3b2d938",
      "title": "",
      "fullFile": "cypress\\e2e\\unlimited-training\\manager\\contact_us.cy.ts",
      "file": "cypress\\e2e\\unlimited-training\\manager\\contact_us.cy.ts",
      "beforeHooks": [],
      "afterHooks": [],
      "tests": [],
      "suites": [
        {
          "uuid": "2248b899-6fa2-4986-bc12-f1a9f903c0a4",
          "title": "UT : Manager : Contact Us",
          "fullFile": "",
          "file": "",
          "beforeHooks": [],
          "afterHooks": [],
          "tests": [
            {
              "title": "Default items should visible",
              "fullTitle": "UT : Manager : Contact Us Default items should visible",
              "timedOut": null,
              "duration": 23254,
              "state": "passed",
              "speed": "slow",
              "pass": true,
              "fail": false,
              "pending": false,
              "context": null,
              "code": "CONTACT_US.verifyItemsIfExist();",
              "err": {},
              "uuid": "103ad64b-094f-4cc7-8ab6-da6e89d1d745",
              "parentUUID": "2248b899-6fa2-4986-bc12-f1a9f903c0a4",
              "isHook": false,
              "skipped": false
            },
            {
              "title": "Check texts/labels if visible",
              "fullTitle": "UT : Manager : Contact Us Check texts/labels if visible",
              "timedOut": null,
              "duration": 136,
              "state": "passed",
              "speed": "fast",
              "pass": true,
              "fail": false,
              "pending": false,
              "context": null,
              "code": "CONTACT_US.verifyTextsIfContains();",
              "err": {},
              "uuid": "cc2a1bfa-021d-486d-a7ae-8f41234f9469",
              "parentUUID": "2248b899-6fa2-4986-bc12-f1a9f903c0a4",
              "isHook": false,
              "skipped": false
            },
            {
              "title": "Validate Cancel submission",
              "fullTitle": "UT : Manager : Contact Us Validate Cancel submission",
              "timedOut": null,
              "duration": 2515,
              "state": "passed",
              "speed": "fast",
              "pass": true,
              "fail": false,
              "pending": false,
              "context": null,
              "code": "CONTACT_US.cancelSubmission();",
              "err": {},
              "uuid": "14af2e97-20f4-4dcb-9b2c-20bf1fd84e1c",
              "parentUUID": "2248b899-6fa2-4986-bc12-f1a9f903c0a4",
              "isHook": false,
              "skipped": false
            },
            {
              "title": "Validate contact-us submission",
              "fullTitle": "UT : Manager : Contact Us Validate contact-us submission",
              "timedOut": null,
              "duration": 10336,
              "state": "passed",
              "speed": "slow",
              "pass": true,
              "fail": false,
              "pending": false,
              "context": null,
              "code": "SIDE_NAV_BAR.editProfile();\nCONTACT_US.viewContactUsTab();\nCONTACT_US.submitContactUs();",
              "err": {},
              "uuid": "db52623b-9bff-4524-b6fb-85443fe5b5ac",
              "parentUUID": "2248b899-6fa2-4986-bc12-f1a9f903c0a4",
              "isHook": false,
              "skipped": false
            }
          ],
          "suites": [],
          "passes": [
            "103ad64b-094f-4cc7-8ab6-da6e89d1d745",
            "cc2a1bfa-021d-486d-a7ae-8f41234f9469",
            "14af2e97-20f4-4dcb-9b2c-20bf1fd84e1c",
            "db52623b-9bff-4524-b6fb-85443fe5b5ac"
          ],
          "failures": [],
          "pending": [],
          "skipped": [],
          "duration": 36241,
          "root": false,
          "rootEmpty": false,
          "_timeout": 2000
        }
      ],
      "passes": [],
      "failures": [],
      "pending": [],
      "skipped": [],
      "duration": 0,
      "root": true,
      "rootEmpty": true,
      "_timeout": 2000
    },
    {
      "uuid": "8423753e-cb54-489b-9c9d-f53fb6d69791",
      "title": "",
      "fullFile": "cypress\\e2e\\unlimited-training\\manager\\profile.cy.ts",
      "file": "cypress\\e2e\\unlimited-training\\manager\\profile.cy.ts",
      "beforeHooks": [],
      "afterHooks": [],
      "tests": [],
      "suites": [
        {
          "uuid": "a82fad17-bd5d-45e6-8776-bdccbd903d14",
          "title": "UT : Manager : General",
          "fullFile": "",
          "file": "",
          "beforeHooks": [],
          "afterHooks": [],
          "tests": [
            {
              "title": "Application Menu : Default items should visible",
              "fullTitle": "UT : Manager : General Application Menu : Default items should visible",
              "timedOut": null,
              "duration": 26345,
              "state": "passed",
              "speed": "slow",
              "pass": true,
              "fail": false,
              "pending": false,
              "context": null,
              "code": "SIDE_NAV_BAR.verifyItemsIfExist('M');",
              "err": {},
              "uuid": "023742f3-f5ee-4f93-a44c-0fe00163386f",
              "parentUUID": "a82fad17-bd5d-45e6-8776-bdccbd903d14",
              "isHook": false,
              "skipped": false
            },
            {
              "title": "Application Menu : Check texts/labels if visible",
              "fullTitle": "UT : Manager : General Application Menu : Check texts/labels if visible",
              "timedOut": null,
              "duration": 17,
              "state": "passed",
              "speed": "fast",
              "pass": true,
              "fail": false,
              "pending": false,
              "context": null,
              "code": "SIDE_NAV_BAR.verifyTextsIfContains('M');",
              "err": {},
              "uuid": "7b950df4-549d-4c46-87bc-3ae565efc55a",
              "parentUUID": "a82fad17-bd5d-45e6-8776-bdccbd903d14",
              "isHook": false,
              "skipped": false
            },
            {
              "title": "Application Menu : Validate favorite application",
              "fullTitle": "UT : Manager : General Application Menu : Validate favorite application",
              "timedOut": null,
              "duration": 5841,
              "state": "passed",
              "speed": "medium",
              "pass": true,
              "fail": false,
              "pending": false,
              "context": null,
              "code": "SIDE_NAV_BAR.favoriteApp('assertAll');",
              "err": {},
              "uuid": "a882c613-a6d1-43ee-b30a-d415466bddbb",
              "parentUUID": "a82fad17-bd5d-45e6-8776-bdccbd903d14",
              "isHook": false,
              "skipped": false
            },
            {
              "title": "My Profile : Default items and fields should visible",
              "fullTitle": "UT : Manager : General My Profile : Default items and fields should visible",
              "timedOut": null,
              "duration": 2371,
              "state": "passed",
              "speed": "fast",
              "pass": true,
              "fail": false,
              "pending": false,
              "context": null,
              "code": "SIDE_NAV_BAR.editProfile();\nMY_PROFILE.verifyItemsIfExist('UT', 'M');",
              "err": {},
              "uuid": "734fa65b-5f7b-4a72-a924-a5de90adbec8",
              "parentUUID": "a82fad17-bd5d-45e6-8776-bdccbd903d14",
              "isHook": false,
              "skipped": false
            },
            {
              "title": "My Profile : Check texts/labels if visible",
              "fullTitle": "UT : Manager : General My Profile : Check texts/labels if visible",
              "timedOut": null,
              "duration": 86,
              "state": "passed",
              "speed": "fast",
              "pass": true,
              "fail": false,
              "pending": false,
              "context": null,
              "code": "MY_PROFILE.verifyTextsIfContains('UT', 'M');",
              "err": {},
              "uuid": "dba45361-b775-47fe-a1c9-3c3e41eb143d",
              "parentUUID": "a82fad17-bd5d-45e6-8776-bdccbd903d14",
              "isHook": false,
              "skipped": false
            },
            {
              "title": "My Profile : Update Basic Information",
              "fullTitle": "UT : Manager : General My Profile : Update Basic Information",
              "timedOut": null,
              "duration": 9603,
              "state": "passed",
              "speed": "medium",
              "pass": true,
              "fail": false,
              "pending": false,
              "context": null,
              "code": "MY_PROFILE.profile('update_basic_info', 'UT', '');",
              "err": {},
              "uuid": "5fe77268-d9c0-4cb7-8aa6-337196e17ab9",
              "parentUUID": "a82fad17-bd5d-45e6-8776-bdccbd903d14",
              "isHook": false,
              "skipped": false
            },
            {
              "title": "My Profile (NEGATIVE) : Invalidate Update button with empty mandatory fields",
              "fullTitle": "UT : Manager : General My Profile (NEGATIVE) : Invalidate Update button with empty mandatory fields",
              "timedOut": null,
              "duration": 5590,
              "state": "passed",
              "speed": "medium",
              "pass": true,
              "fail": false,
              "pending": false,
              "context": null,
              "code": "MY_PROFILE.profile('clear_all_fields', '', '');",
              "err": {},
              "uuid": "77b580bd-6269-45a0-93b7-4827cf77e7f0",
              "parentUUID": "a82fad17-bd5d-45e6-8776-bdccbd903d14",
              "isHook": false,
              "skipped": false
            },
            {
              "title": "My Profile (NEGATIVE) : Password and verify fields password does not match",
              "fullTitle": "UT : Manager : General My Profile (NEGATIVE) : Password and verify fields password does not match",
              "timedOut": null,
              "duration": 5213,
              "state": "passed",
              "speed": "medium",
              "pass": true,
              "fail": false,
              "pending": false,
              "context": null,
              "code": "MY_PROFILE.profile('un_matched_password', '', '');",
              "err": {},
              "uuid": "ddf4c7eb-87cb-40a8-9745-feb4358d4173",
              "parentUUID": "a82fad17-bd5d-45e6-8776-bdccbd903d14",
              "isHook": false,
              "skipped": false
            },
            {
              "title": "My Profile (EDGE CASE) : Add alphabet and special character on phone number",
              "fullTitle": "UT : Manager : General My Profile (EDGE CASE) : Add alphabet and special character on phone number",
              "timedOut": null,
              "duration": 5947,
              "state": "passed",
              "speed": "medium",
              "pass": true,
              "fail": false,
              "pending": false,
              "context": null,
              "code": "MY_PROFILE.profile('validate_phone_number', '', '');",
              "err": {},
              "uuid": "0301aaa0-3d58-423d-b024-9cab8af0979c",
              "parentUUID": "a82fad17-bd5d-45e6-8776-bdccbd903d14",
              "isHook": false,
              "skipped": false
            },
            {
              "title": "My Profile (EDGE CASE) : Add alphabet and special character on mobile number",
              "fullTitle": "UT : Manager : General My Profile (EDGE CASE) : Add alphabet and special character on mobile number",
              "timedOut": null,
              "duration": 5365,
              "state": "passed",
              "speed": "medium",
              "pass": true,
              "fail": false,
              "pending": false,
              "context": null,
              "code": "MY_PROFILE.profile('validate_mobile_number', '', '');",
              "err": {},
              "uuid": "aee3cc17-1946-4a41-8cec-dfe113b54952",
              "parentUUID": "a82fad17-bd5d-45e6-8776-bdccbd903d14",
              "isHook": false,
              "skipped": false
            },
            {
              "title": "My Profile (OOTB) : Able to change country code on phone number",
              "fullTitle": "UT : Manager : General My Profile (OOTB) : Able to change country code on phone number",
              "timedOut": null,
              "duration": 4111,
              "state": "passed",
              "speed": "fast",
              "pass": true,
              "fail": false,
              "pending": false,
              "context": null,
              "code": "MY_PROFILE.profile('validate_mobile_country_code', '', '');",
              "err": {},
              "uuid": "c435a243-eb31-4851-859a-d47cd4ec97ab",
              "parentUUID": "a82fad17-bd5d-45e6-8776-bdccbd903d14",
              "isHook": false,
              "skipped": false
            },
            {
              "title": "My Profile (OOTB) : Disable update button when mandatory fields are empty",
              "fullTitle": "UT : Manager : General My Profile (OOTB) : Disable update button when mandatory fields are empty",
              "timedOut": null,
              "duration": 5282,
              "state": "passed",
              "speed": "medium",
              "pass": true,
              "fail": false,
              "pending": false,
              "context": null,
              "code": "MY_PROFILE.profile('disable_update_button', '', '');",
              "err": {},
              "uuid": "f9b3952b-5d52-40f1-94a9-f4141db6b637",
              "parentUUID": "a82fad17-bd5d-45e6-8776-bdccbd903d14",
              "isHook": false,
              "skipped": false
            },
            {
              "title": "My Profile : Validate Password Strength - risk",
              "fullTitle": "UT : Manager : General My Profile : Validate Password Strength - risk",
              "timedOut": null,
              "duration": 363,
              "state": "passed",
              "speed": "fast",
              "pass": true,
              "fail": false,
              "pending": false,
              "context": null,
              "code": "COMM_ELEMENTS.passwordStrength('risky');",
              "err": {},
              "uuid": "1064c18f-e6b2-4326-bc30-58bd31b3e668",
              "parentUUID": "a82fad17-bd5d-45e6-8776-bdccbd903d14",
              "isHook": false,
              "skipped": false
            },
            {
              "title": "My Profile : Validate Password Strength - weak",
              "fullTitle": "UT : Manager : General My Profile : Validate Password Strength - weak",
              "timedOut": null,
              "duration": 382,
              "state": "passed",
              "speed": "fast",
              "pass": true,
              "fail": false,
              "pending": false,
              "context": null,
              "code": "COMM_ELEMENTS.passwordStrength('weak');",
              "err": {},
              "uuid": "32253026-aa85-4a9d-8c3a-361530134e03",
              "parentUUID": "a82fad17-bd5d-45e6-8776-bdccbd903d14",
              "isHook": false,
              "skipped": false
            },
            {
              "title": "My Profile : Validate Password Strength - fair",
              "fullTitle": "UT : Manager : General My Profile : Validate Password Strength - fair",
              "timedOut": null,
              "duration": 551,
              "state": "passed",
              "speed": "fast",
              "pass": true,
              "fail": false,
              "pending": false,
              "context": null,
              "code": "COMM_ELEMENTS.passwordStrength('fair');",
              "err": {},
              "uuid": "d0291bf8-a4ec-4493-978c-e4eb68d9ce96",
              "parentUUID": "a82fad17-bd5d-45e6-8776-bdccbd903d14",
              "isHook": false,
              "skipped": false
            },
            {
              "title": "My Profile : Validate Password Strength - good",
              "fullTitle": "UT : Manager : General My Profile : Validate Password Strength - good",
              "timedOut": null,
              "duration": 574,
              "state": "passed",
              "speed": "fast",
              "pass": true,
              "fail": false,
              "pending": false,
              "context": null,
              "code": "COMM_ELEMENTS.passwordStrength('good');",
              "err": {},
              "uuid": "fb46d96e-1a60-42eb-a6a5-eb9ed1dcb1ec",
              "parentUUID": "a82fad17-bd5d-45e6-8776-bdccbd903d14",
              "isHook": false,
              "skipped": false
            },
            {
              "title": "My Profile : Validate Password Strength - strong",
              "fullTitle": "UT : Manager : General My Profile : Validate Password Strength - strong",
              "timedOut": null,
              "duration": 813,
              "state": "passed",
              "speed": "fast",
              "pass": true,
              "fail": false,
              "pending": false,
              "context": null,
              "code": "COMM_ELEMENTS.passwordStrength('strong');",
              "err": {},
              "uuid": "01eea9fb-fd61-4b1e-b3a6-30cdf4e65ea8",
              "parentUUID": "a82fad17-bd5d-45e6-8776-bdccbd903d14",
              "isHook": false,
              "skipped": false
            }
          ],
          "suites": [],
          "passes": [
            "023742f3-f5ee-4f93-a44c-0fe00163386f",
            "7b950df4-549d-4c46-87bc-3ae565efc55a",
            "a882c613-a6d1-43ee-b30a-d415466bddbb",
            "734fa65b-5f7b-4a72-a924-a5de90adbec8",
            "dba45361-b775-47fe-a1c9-3c3e41eb143d",
            "5fe77268-d9c0-4cb7-8aa6-337196e17ab9",
            "77b580bd-6269-45a0-93b7-4827cf77e7f0",
            "ddf4c7eb-87cb-40a8-9745-feb4358d4173",
            "0301aaa0-3d58-423d-b024-9cab8af0979c",
            "aee3cc17-1946-4a41-8cec-dfe113b54952",
            "c435a243-eb31-4851-859a-d47cd4ec97ab",
            "f9b3952b-5d52-40f1-94a9-f4141db6b637",
            "1064c18f-e6b2-4326-bc30-58bd31b3e668",
            "32253026-aa85-4a9d-8c3a-361530134e03",
            "d0291bf8-a4ec-4493-978c-e4eb68d9ce96",
            "fb46d96e-1a60-42eb-a6a5-eb9ed1dcb1ec",
            "01eea9fb-fd61-4b1e-b3a6-30cdf4e65ea8"
          ],
          "failures": [],
          "pending": [],
          "skipped": [],
          "duration": 78454,
          "root": false,
          "rootEmpty": false,
          "_timeout": 2000
        }
      ],
      "passes": [],
      "failures": [],
      "pending": [],
      "skipped": [],
      "duration": 0,
      "root": true,
      "rootEmpty": true,
      "_timeout": 2000
    },
    {
      "uuid": "42234138-3e1c-4c00-bf95-39767bcba330",
      "title": "",
      "fullFile": "cypress\\e2e\\unlimited-training\\manager\\reg_codes.cy.ts",
      "file": "cypress\\e2e\\unlimited-training\\manager\\reg_codes.cy.ts",
      "beforeHooks": [],
      "afterHooks": [],
      "tests": [],
      "suites": [
        {
          "uuid": "ad919fd6-f6a1-443a-901f-a4c150bd5cab",
          "title": "UT : Add New Managers : Registration codes",
          "fullFile": "",
          "file": "",
          "beforeHooks": [],
          "afterHooks": [],
          "tests": [
            {
              "title": "Default items should visible",
              "fullTitle": "UT : Add New Managers : Registration codes Default items should visible",
              "timedOut": null,
              "duration": 2765,
              "state": "passed",
              "speed": "fast",
              "pass": true,
              "fail": false,
              "pending": false,
              "context": null,
              "code": "NEW_USER.register('default_items', null);",
              "err": {},
              "uuid": "b6d21b8b-dd52-4a80-9b6c-be4c584ea37e",
              "parentUUID": "ad919fd6-f6a1-443a-901f-a4c150bd5cab",
              "isHook": false,
              "skipped": false
            },
            {
              "title": "Validate successful new user account creation",
              "fullTitle": "UT : Add New Managers : Registration codes Validate successful new user account creation",
              "timedOut": null,
              "duration": 18682,
              "state": "passed",
              "speed": "slow",
              "pass": true,
              "fail": false,
              "pending": false,
              "context": null,
              "code": "NEW_USER.register('add_user', 'success_creation');",
              "err": {},
              "uuid": "03432fe1-de34-4766-80ab-655fb3d6b65e",
              "parentUUID": "ad919fd6-f6a1-443a-901f-a4c150bd5cab",
              "isHook": false,
              "skipped": false
            },
            {
              "title": "Validate existing user",
              "fullTitle": "UT : Add New Managers : Registration codes Validate existing user",
              "timedOut": null,
              "duration": 16368,
              "state": "passed",
              "speed": "slow",
              "pass": true,
              "fail": false,
              "pending": false,
              "context": null,
              "code": "NEW_USER.register('add_user', 'already_exist');",
              "err": {},
              "uuid": "12d4df53-c40e-4b23-bc38-591d35b85e82",
              "parentUUID": "ad919fd6-f6a1-443a-901f-a4c150bd5cab",
              "isHook": false,
              "skipped": false
            },
            {
              "title": "Validate cancel adding new user",
              "fullTitle": "UT : Add New Managers : Registration codes Validate cancel adding new user",
              "timedOut": null,
              "duration": 298,
              "state": "passed",
              "speed": "fast",
              "pass": true,
              "fail": false,
              "pending": false,
              "context": null,
              "code": "cy.visit(Cypress.env(\"url\"));\nNEW_USER.register('cancel_creating_user', null);",
              "err": {},
              "uuid": "ef85e521-4e01-444f-a317-6132102e576f",
              "parentUUID": "ad919fd6-f6a1-443a-901f-a4c150bd5cab",
              "isHook": false,
              "skipped": false
            },
            {
              "title": "Check field validations",
              "fullTitle": "UT : Add New Managers : Registration codes Check field validations",
              "timedOut": null,
              "duration": 1688,
              "state": "passed",
              "speed": "fast",
              "pass": true,
              "fail": false,
              "pending": false,
              "context": null,
              "code": "NEW_USER.register('disable_submit_button', null);",
              "err": {},
              "uuid": "dbb0d71e-7449-484a-a298-6ba45e1a3bed",
              "parentUUID": "ad919fd6-f6a1-443a-901f-a4c150bd5cab",
              "isHook": false,
              "skipped": false
            },
            {
              "title": "Validate matching email and confirm email fields",
              "fullTitle": "UT : Add New Managers : Registration codes Validate matching email and confirm email fields",
              "timedOut": null,
              "duration": 5174,
              "state": "passed",
              "speed": "medium",
              "pass": true,
              "fail": false,
              "pending": false,
              "context": null,
              "code": "NEW_USER.register('validation_fields', 'email_not_matched');",
              "err": {},
              "uuid": "b47d3e0c-9eeb-4090-99ba-a979f446ebb0",
              "parentUUID": "ad919fd6-f6a1-443a-901f-a4c150bd5cab",
              "isHook": false,
              "skipped": false
            },
            {
              "title": "Validate matching password and verify password fields",
              "fullTitle": "UT : Add New Managers : Registration codes Validate matching password and verify password fields",
              "timedOut": null,
              "duration": 4369,
              "state": "passed",
              "speed": "fast",
              "pass": true,
              "fail": false,
              "pending": false,
              "context": null,
              "code": "cy.visit(Cypress.env(\"url\"));\nNEW_USER.register('validation_fields', 'passwords_not_matched');",
              "err": {},
              "uuid": "a75c9f99-0044-4b49-9603-9ef19d82ebc3",
              "parentUUID": "ad919fd6-f6a1-443a-901f-a4c150bd5cab",
              "isHook": false,
              "skipped": false
            },
            {
              "title": "Create account : Validate Password Strength - risk",
              "fullTitle": "UT : Add New Managers : Registration codes Create account : Validate Password Strength - risk",
              "timedOut": null,
              "duration": 449,
              "state": "passed",
              "speed": "fast",
              "pass": true,
              "fail": false,
              "pending": false,
              "context": null,
              "code": "NEW_USER.newUser.click();\nCOMM_ELEMENTS.passwordStrength('risky');",
              "err": {},
              "uuid": "14b90356-4b0d-43ee-8994-76d2ca4c91d4",
              "parentUUID": "ad919fd6-f6a1-443a-901f-a4c150bd5cab",
              "isHook": false,
              "skipped": false
            },
            {
              "title": "Create account : Validate Password Strength - weak",
              "fullTitle": "UT : Add New Managers : Registration codes Create account : Validate Password Strength - weak",
              "timedOut": null,
              "duration": 464,
              "state": "passed",
              "speed": "fast",
              "pass": true,
              "fail": false,
              "pending": false,
              "context": null,
              "code": "NEW_USER.newUser.click();\nCOMM_ELEMENTS.passwordStrength('weak');",
              "err": {},
              "uuid": "2906635c-faaf-4e53-b4f4-157b8bf88cff",
              "parentUUID": "ad919fd6-f6a1-443a-901f-a4c150bd5cab",
              "isHook": false,
              "skipped": false
            },
            {
              "title": "Create account : Validate Password Strength - fair",
              "fullTitle": "UT : Add New Managers : Registration codes Create account : Validate Password Strength - fair",
              "timedOut": null,
              "duration": 526,
              "state": "passed",
              "speed": "fast",
              "pass": true,
              "fail": false,
              "pending": false,
              "context": null,
              "code": "cy.visit(Cypress.env(\"url\"));\nNEW_USER.newUser.click();\nCOMM_ELEMENTS.passwordStrength('fair');",
              "err": {},
              "uuid": "ed56825f-eb34-46d5-8e50-e187a8ce1bdb",
              "parentUUID": "ad919fd6-f6a1-443a-901f-a4c150bd5cab",
              "isHook": false,
              "skipped": false
            },
            {
              "title": "Create account : Validate Password Strength - good",
              "fullTitle": "UT : Add New Managers : Registration codes Create account : Validate Password Strength - good",
              "timedOut": null,
              "duration": 580,
              "state": "passed",
              "speed": "fast",
              "pass": true,
              "fail": false,
              "pending": false,
              "context": null,
              "code": "NEW_USER.newUser.click();\nCOMM_ELEMENTS.passwordStrength('good');",
              "err": {},
              "uuid": "22d14109-5662-46b7-a466-9f25d93c43af",
              "parentUUID": "ad919fd6-f6a1-443a-901f-a4c150bd5cab",
              "isHook": false,
              "skipped": false
            },
            {
              "title": "Create account : Validate Password Strength - strong",
              "fullTitle": "UT : Add New Managers : Registration codes Create account : Validate Password Strength - strong",
              "timedOut": null,
              "duration": 657,
              "state": "passed",
              "speed": "fast",
              "pass": true,
              "fail": false,
              "pending": false,
              "context": null,
              "code": "NEW_USER.newUser.click();\nCOMM_ELEMENTS.passwordStrength('strong');",
              "err": {},
              "uuid": "c2d311f9-36b3-4a8a-80dd-3cee15295d5d",
              "parentUUID": "ad919fd6-f6a1-443a-901f-a4c150bd5cab",
              "isHook": false,
              "skipped": false
            }
          ],
          "suites": [],
          "passes": [
            "b6d21b8b-dd52-4a80-9b6c-be4c584ea37e",
            "03432fe1-de34-4766-80ab-655fb3d6b65e",
            "12d4df53-c40e-4b23-bc38-591d35b85e82",
            "ef85e521-4e01-444f-a317-6132102e576f",
            "dbb0d71e-7449-484a-a298-6ba45e1a3bed",
            "b47d3e0c-9eeb-4090-99ba-a979f446ebb0",
            "a75c9f99-0044-4b49-9603-9ef19d82ebc3",
            "14b90356-4b0d-43ee-8994-76d2ca4c91d4",
            "2906635c-faaf-4e53-b4f4-157b8bf88cff",
            "ed56825f-eb34-46d5-8e50-e187a8ce1bdb",
            "22d14109-5662-46b7-a466-9f25d93c43af",
            "c2d311f9-36b3-4a8a-80dd-3cee15295d5d"
          ],
          "failures": [],
          "pending": [],
          "skipped": [],
          "duration": 52020,
          "root": false,
          "rootEmpty": false,
          "_timeout": 2000
        }
      ],
      "passes": [],
      "failures": [],
      "pending": [],
      "skipped": [],
      "duration": 0,
      "root": true,
      "rootEmpty": true,
      "_timeout": 2000
    },
    {
      "uuid": "a64f09ae-2954-4673-992f-78cf8e5e4764",
      "title": "",
      "fullFile": "cypress\\e2e\\unlimited-training\\manager\\my-company\\company_dark_web.cy.ts",
      "file": "cypress\\e2e\\unlimited-training\\manager\\my-company\\company_dark_web.cy.ts",
      "beforeHooks": [],
      "afterHooks": [],
      "tests": [],
      "suites": [
        {
          "uuid": "6d9bd447-729f-4d63-97ab-bc3f62c177bb",
          "title": "UT : Manager : Company : Dark Web Monitoring",
          "fullFile": "",
          "file": "",
          "beforeHooks": [],
          "afterHooks": [],
          "tests": [
            {
              "title": "Default items should visible",
              "fullTitle": "UT : Manager : Company : Dark Web Monitoring Default items should visible",
              "timedOut": null,
              "duration": 30876,
              "state": "passed",
              "speed": "slow",
              "pass": true,
              "fail": false,
              "pending": false,
              "context": null,
              "code": "DARK_WEB.validateScenario('default_items');\nCOMM_ELEMENTS.hideLoadingScreen();",
              "err": {},
              "uuid": "d936d462-9a15-4548-b650-8bbe039926ea",
              "parentUUID": "6d9bd447-729f-4d63-97ab-bc3f62c177bb",
              "isHook": false,
              "skipped": false
            },
            {
              "title": "Generate Reports",
              "fullTitle": "UT : Manager : Company : Dark Web Monitoring Generate Reports",
              "timedOut": null,
              "duration": 5288,
              "state": "failed",
              "speed": null,
              "pass": false,
              "fail": true,
              "pending": false,
              "context": null,
              "code": "DARK_WEB.validateScenario('api_report');",
              "err": {
                "message": "CypressError: Timed out retrying after 5000ms: `cy.wait()` timed out waiting `5000ms` for the 1st request to the route: `domains_list`. No request ever occurred.\n\nhttps://on.cypress.io/wait\n\nBecause this error occurred during a `before each` hook we are skipping all of the remaining tests.",
                "estack": "CypressError: Timed out retrying after 5000ms: `cy.wait()` timed out waiting `5000ms` for the 1st request to the route: `domains_list`. No request ever occurred.\n\nhttps://on.cypress.io/wait\n\nBecause this error occurred during a `before each` hook we are skipping all of the remaining tests.\n    at cypressErr (https://portal.breachsecurenow.com/__cypress/runner/cypress_runner.js:77680:18)\n    at Object.errByPath (https://portal.breachsecurenow.com/__cypress/runner/cypress_runner.js:77734:10)\n    at checkForXhr (https://portal.breachsecurenow.com/__cypress/runner/cypress_runner.js:138761:84)\n    at <unknown> (https://portal.breachsecurenow.com/__cypress/runner/cypress_runner.js:138787:28)\n    at tryCatcher (https://portal.breachsecurenow.com/__cypress/runner/cypress_runner.js:1777:23)\n    at Promise.attempt.Promise.try (https://portal.breachsecurenow.com/__cypress/runner/cypress_runner.js:4285:29)\n    at whenStable (https://portal.breachsecurenow.com/__cypress/runner/cypress_runner.js:147197:68)\n    at <unknown> (https://portal.breachsecurenow.com/__cypress/runner/cypress_runner.js:147138:14)\n    at tryCatcher (https://portal.breachsecurenow.com/__cypress/runner/cypress_runner.js:1777:23)\n    at Promise._settlePromiseFromHandler (https://portal.breachsecurenow.com/__cypress/runner/cypress_runner.js:1489:31)\n    at Promise._settlePromise (https://portal.breachsecurenow.com/__cypress/runner/cypress_runner.js:1546:18)\n    at Promise._settlePromise0 (https://portal.breachsecurenow.com/__cypress/runner/cypress_runner.js:1591:10)\n    at Promise._settlePromises (https://portal.breachsecurenow.com/__cypress/runner/cypress_runner.js:1671:18)\n    at Promise._fulfill (https://portal.breachsecurenow.com/__cypress/runner/cypress_runner.js:1615:18)\n    at <unknown> (https://portal.breachsecurenow.com/__cypress/runner/cypress_runner.js:5420:46)",
                "diff": null
              },
              "uuid": "ca6c2a00-4bf2-4610-bd10-46c9196c5ae0",
              "parentUUID": "6d9bd447-729f-4d63-97ab-bc3f62c177bb",
              "isHook": false,
              "skipped": false
            },
            {
              "title": "Validate API results when generating reports",
              "fullTitle": "UT : Manager : Company : Dark Web Monitoring Validate API results when generating reports",
              "timedOut": null,
              "duration": 0,
              "state": "skipped",
              "speed": null,
              "pass": false,
              "fail": false,
              "pending": false,
              "context": null,
              "code": "DARK_WEB.validateScenario('generate_results');",
              "err": {},
              "uuid": "ce245234-1f82-460d-a5f0-2798c1ea95ca",
              "parentUUID": "6d9bd447-729f-4d63-97ab-bc3f62c177bb",
              "isHook": false,
              "skipped": true
            },
            {
              "title": "Validate POST method each click event on table results",
              "fullTitle": "UT : Manager : Company : Dark Web Monitoring Validate POST method each click event on table results",
              "timedOut": null,
              "duration": 0,
              "state": "skipped",
              "speed": null,
              "pass": false,
              "fail": false,
              "pending": false,
              "context": null,
              "code": "DARK_WEB.validateScenario('refresh_session_event');",
              "err": {},
              "uuid": "50c87a98-dc46-4633-bc0a-298c02dd6c6c",
              "parentUUID": "6d9bd447-729f-4d63-97ab-bc3f62c177bb",
              "isHook": false,
              "skipped": true
            },
            {
              "title": "Validate unregistered domain on table results",
              "fullTitle": "UT : Manager : Company : Dark Web Monitoring Validate unregistered domain on table results",
              "timedOut": null,
              "duration": 0,
              "state": "skipped",
              "speed": null,
              "pass": false,
              "fail": false,
              "pending": false,
              "context": null,
              "code": "DARK_WEB.validateScenario('search_unregistered_domains');",
              "err": {},
              "uuid": "e0c98b0f-1cff-4fd7-b329-7f92ae618baf",
              "parentUUID": "6d9bd447-729f-4d63-97ab-bc3f62c177bb",
              "isHook": false,
              "skipped": true
            },
            {
              "title": "Validate unlisted site breached on table results",
              "fullTitle": "UT : Manager : Company : Dark Web Monitoring Validate unlisted site breached on table results",
              "timedOut": null,
              "duration": 0,
              "state": "skipped",
              "speed": null,
              "pass": false,
              "fail": false,
              "pending": false,
              "context": null,
              "code": "DARK_WEB.validateScenario('search_unlisted_site_breached');",
              "err": {},
              "uuid": "cfef70d0-c7ba-4330-88cb-8a97ae6b1d3b",
              "parentUUID": "6d9bd447-729f-4d63-97ab-bc3f62c177bb",
              "isHook": false,
              "skipped": true
            },
            {
              "title": "Invalidate searching breach date",
              "fullTitle": "UT : Manager : Company : Dark Web Monitoring Invalidate searching breach date",
              "timedOut": null,
              "duration": 0,
              "state": "skipped",
              "speed": null,
              "pass": false,
              "fail": false,
              "pending": false,
              "context": null,
              "code": "DARK_WEB.validateScenario('search_breach_date');",
              "err": {},
              "uuid": "1a63d397-7948-4b51-9746-dd7f5178b1a2",
              "parentUUID": "6d9bd447-729f-4d63-97ab-bc3f62c177bb",
              "isHook": false,
              "skipped": true
            },
            {
              "title": "Validate password redaction options",
              "fullTitle": "UT : Manager : Company : Dark Web Monitoring Validate password redaction options",
              "timedOut": null,
              "duration": 0,
              "state": "skipped",
              "speed": null,
              "pass": false,
              "fail": false,
              "pending": false,
              "context": null,
              "code": "DARK_WEB.validateScenario('obfuscate_password');",
              "err": {},
              "uuid": "582e56aa-f001-4182-a4c6-81812e021678",
              "parentUUID": "6d9bd447-729f-4d63-97ab-bc3f62c177bb",
              "isHook": false,
              "skipped": true
            },
            {
              "title": "Validate non redaction password",
              "fullTitle": "UT : Manager : Company : Dark Web Monitoring Validate non redaction password",
              "timedOut": null,
              "duration": 0,
              "state": "skipped",
              "speed": null,
              "pass": false,
              "fail": false,
              "pending": false,
              "context": null,
              "code": "DARK_WEB.validateScenario('non_redacted_password');",
              "err": {},
              "uuid": "84b4ceed-a577-4023-bf66-809a9ec7de24",
              "parentUUID": "6d9bd447-729f-4d63-97ab-bc3f62c177bb",
              "isHook": false,
              "skipped": true
            },
            {
              "title": "Validate column sorting",
              "fullTitle": "UT : Manager : Company : Dark Web Monitoring Validate column sorting",
              "timedOut": null,
              "duration": 0,
              "state": "skipped",
              "speed": null,
              "pass": false,
              "fail": false,
              "pending": false,
              "context": null,
              "code": "DARK_WEB.validateScenario('column_sorting');",
              "err": {},
              "uuid": "ab040fac-fe2e-4652-af3a-b613646e84e3",
              "parentUUID": "6d9bd447-729f-4d63-97ab-bc3f62c177bb",
              "isHook": false,
              "skipped": true
            }
          ],
          "suites": [],
          "passes": [
            "d936d462-9a15-4548-b650-8bbe039926ea"
          ],
          "failures": [
            "ca6c2a00-4bf2-4610-bd10-46c9196c5ae0"
          ],
          "pending": [],
          "skipped": [
            "ce245234-1f82-460d-a5f0-2798c1ea95ca",
            "50c87a98-dc46-4633-bc0a-298c02dd6c6c",
            "e0c98b0f-1cff-4fd7-b329-7f92ae618baf",
            "cfef70d0-c7ba-4330-88cb-8a97ae6b1d3b",
            "1a63d397-7948-4b51-9746-dd7f5178b1a2",
            "582e56aa-f001-4182-a4c6-81812e021678",
            "84b4ceed-a577-4023-bf66-809a9ec7de24",
            "ab040fac-fe2e-4652-af3a-b613646e84e3"
          ],
          "duration": 36164,
          "root": false,
          "rootEmpty": false,
          "_timeout": 2000
        }
      ],
      "passes": [],
      "failures": [],
      "pending": [],
      "skipped": [],
      "duration": 0,
      "root": true,
      "rootEmpty": true,
      "_timeout": 2000
    },
    {
      "uuid": "dffbd8b9-282f-469d-b68c-39b18c4c7a7f",
      "title": "",
      "fullFile": "cypress\\e2e\\unlimited-training\\manager\\my-dashboard\\manager_training.cy.ts",
      "file": "cypress\\e2e\\unlimited-training\\manager\\my-dashboard\\manager_training.cy.ts",
      "beforeHooks": [],
      "afterHooks": [],
      "tests": [],
      "suites": [
        {
          "uuid": "1fe40b8f-37db-4f9a-ac20-205cd3813b01",
          "title": "UT : Manager : Dashboard : Training",
          "fullFile": "",
          "file": "",
          "beforeHooks": [],
          "afterHooks": [],
          "tests": [
            {
              "title": "Training : Default items should visible",
              "fullTitle": "UT : Manager : Dashboard : Training Training : Default items should visible",
              "timedOut": null,
              "duration": 35165,
              "state": "passed",
              "speed": "slow",
              "pass": true,
              "fail": false,
              "pending": false,
              "context": null,
              "code": "TRAINING.completedCourses('default_items');",
              "err": {},
              "uuid": "e6c53f49-075e-480b-9791-73a8c1f17bb9",
              "parentUUID": "1fe40b8f-37db-4f9a-ac20-205cd3813b01",
              "isHook": false,
              "skipped": false
            },
            {
              "title": "Training : Check texts/labels if visible",
              "fullTitle": "UT : Manager : Dashboard : Training Training : Check texts/labels if visible",
              "timedOut": null,
              "duration": 10131,
              "state": "passed",
              "speed": "slow",
              "pass": true,
              "fail": false,
              "pending": false,
              "context": null,
              "code": "TRAINING.completedCourses('default_texts');",
              "err": {},
              "uuid": "d1b00ea5-7316-4ff1-bb67-f8cb5f3034d8",
              "parentUUID": "1fe40b8f-37db-4f9a-ac20-205cd3813b01",
              "isHook": false,
              "skipped": false
            },
            {
              "title": "Training : Validate Cybersecurity Training Videos",
              "fullTitle": "UT : Manager : Dashboard : Training Training : Validate Cybersecurity Training Videos",
              "timedOut": null,
              "duration": 21451,
              "state": "passed",
              "speed": "slow",
              "pass": true,
              "fail": false,
              "pending": false,
              "context": null,
              "code": "TRAINING.completedCourses('security_training_videos');",
              "err": {},
              "uuid": "64c92c8d-91ae-4f6b-9a1e-e2f375673799",
              "parentUUID": "1fe40b8f-37db-4f9a-ac20-205cd3813b01",
              "isHook": false,
              "skipped": false
            },
            {
              "title": "Training : Validate Optional Manager Training",
              "fullTitle": "UT : Manager : Dashboard : Training Training : Validate Optional Manager Training",
              "timedOut": null,
              "duration": 11093,
              "state": "passed",
              "speed": "slow",
              "pass": true,
              "fail": false,
              "pending": false,
              "context": null,
              "code": "TRAINING.completedCourses('training_videos');",
              "err": {},
              "uuid": "0f3f9d6e-fdad-44f7-960c-6fbc2bd2d205",
              "parentUUID": "1fe40b8f-37db-4f9a-ac20-205cd3813b01",
              "isHook": false,
              "skipped": false
            },
            {
              "title": "Training (EDGE) : Validate Security Quiz",
              "fullTitle": "UT : Manager : Dashboard : Training Training (EDGE) : Validate Security Quiz",
              "timedOut": null,
              "duration": 6408,
              "state": "passed",
              "speed": "medium",
              "pass": true,
              "fail": false,
              "pending": false,
              "context": null,
              "code": "TRAINING.completedCourses('complete_security_quiz');",
              "err": {},
              "uuid": "47f897ed-2e9a-47dc-b777-16e39ea35b47",
              "parentUUID": "1fe40b8f-37db-4f9a-ac20-205cd3813b01",
              "isHook": false,
              "skipped": false
            },
            {
              "title": "Training (EDGE) : Validate Reviewing Security Quiz",
              "fullTitle": "UT : Manager : Dashboard : Training Training (EDGE) : Validate Reviewing Security Quiz",
              "timedOut": null,
              "duration": 6189,
              "state": "passed",
              "speed": "medium",
              "pass": true,
              "fail": false,
              "pending": false,
              "context": null,
              "code": "TRAINING.completedCourses('review_security_quiz');",
              "err": {},
              "uuid": "0d9a8200-2180-4409-ba73-fb94b5e9f9b5",
              "parentUUID": "1fe40b8f-37db-4f9a-ac20-205cd3813b01",
              "isHook": false,
              "skipped": false
            },
            {
              "title": "Training : Validate Step 3 - Print Your Certificate",
              "fullTitle": "UT : Manager : Dashboard : Training Training : Validate Step 3 - Print Your Certificate",
              "timedOut": null,
              "duration": 23243,
              "state": "passed",
              "speed": "slow",
              "pass": true,
              "fail": false,
              "pending": false,
              "context": null,
              "code": "TRAINING.completedCourses('print_certificate');",
              "err": {},
              "uuid": "97c209d1-50d0-4c67-a247-1adece3dad33",
              "parentUUID": "1fe40b8f-37db-4f9a-ac20-205cd3813b01",
              "isHook": false,
              "skipped": false
            },
            {
              "title": "Validate Enrolled Courses",
              "fullTitle": "UT : Manager : Dashboard : Training Validate Enrolled Courses",
              "timedOut": null,
              "duration": 5166,
              "state": "passed",
              "speed": "medium",
              "pass": true,
              "fail": false,
              "pending": false,
              "context": null,
              "code": "TRAINING.enrolledCourses();",
              "err": {},
              "uuid": "4673efc5-f99f-4ac4-bd20-9e8d54b196e7",
              "parentUUID": "1fe40b8f-37db-4f9a-ac20-205cd3813b01",
              "isHook": false,
              "skipped": false
            }
          ],
          "suites": [],
          "passes": [
            "e6c53f49-075e-480b-9791-73a8c1f17bb9",
            "d1b00ea5-7316-4ff1-bb67-f8cb5f3034d8",
            "64c92c8d-91ae-4f6b-9a1e-e2f375673799",
            "0f3f9d6e-fdad-44f7-960c-6fbc2bd2d205",
            "47f897ed-2e9a-47dc-b777-16e39ea35b47",
            "0d9a8200-2180-4409-ba73-fb94b5e9f9b5",
            "97c209d1-50d0-4c67-a247-1adece3dad33",
            "4673efc5-f99f-4ac4-bd20-9e8d54b196e7"
          ],
          "failures": [],
          "pending": [],
          "skipped": [],
          "duration": 118846,
          "root": false,
          "rootEmpty": false,
          "_timeout": 2000
        }
      ],
      "passes": [],
      "failures": [],
      "pending": [],
      "skipped": [],
      "duration": 0,
      "root": true,
      "rootEmpty": true,
      "_timeout": 2000
    },
    {
      "uuid": "2a56b89d-c828-4da8-922d-ca17f306d298",
      "title": "",
      "fullFile": "cypress\\e2e\\unlimited-training\\manager\\my-company\\employee\\employee.cy.ts",
      "file": "cypress\\e2e\\unlimited-training\\manager\\my-company\\employee\\employee.cy.ts",
      "beforeHooks": [],
      "afterHooks": [],
      "tests": [],
      "suites": [
        {
          "uuid": "aea7bdf7-0eec-41c2-a67d-29bc37431389",
          "title": "UT : Manager : Company : Employee",
          "fullFile": "",
          "file": "",
          "beforeHooks": [],
          "afterHooks": [],
          "tests": [
            {
              "title": "Validated default items should visible",
              "fullTitle": "UT : Manager : Company : Employee Validated default items should visible",
              "timedOut": null,
              "duration": 47525,
              "state": "failed",
              "speed": null,
              "pass": false,
              "fail": true,
              "pending": false,
              "context": null,
              "code": "EMPLOYEES.validateItems('verify-items-if-exist', 'UT', 'M', 'employees');",
              "err": {
                "message": "CypressError: Timed out retrying after 15000ms: `cy.wait()` timed out waiting `15000ms` for the 1st request to the route: `directorySync`. No request ever occurred.\n\nhttps://on.cypress.io/wait",
                "estack": "CypressError: Timed out retrying after 15000ms: `cy.wait()` timed out waiting `15000ms` for the 1st request to the route: `directorySync`. No request ever occurred.\n\nhttps://on.cypress.io/wait\n    at cypressErr (https://portal.breachsecurenow.com/__cypress/runner/cypress_runner.js:77680:18)\n    at Object.errByPath (https://portal.breachsecurenow.com/__cypress/runner/cypress_runner.js:77734:10)\n    at checkForXhr (https://portal.breachsecurenow.com/__cypress/runner/cypress_runner.js:138761:84)\n    at <unknown> (https://portal.breachsecurenow.com/__cypress/runner/cypress_runner.js:138787:28)\n    at tryCatcher (https://portal.breachsecurenow.com/__cypress/runner/cypress_runner.js:1777:23)\n    at Promise.attempt.Promise.try (https://portal.breachsecurenow.com/__cypress/runner/cypress_runner.js:4285:29)\n    at whenStable (https://portal.breachsecurenow.com/__cypress/runner/cypress_runner.js:147197:68)\n    at <unknown> (https://portal.breachsecurenow.com/__cypress/runner/cypress_runner.js:147138:14)\n    at tryCatcher (https://portal.breachsecurenow.com/__cypress/runner/cypress_runner.js:1777:23)\n    at Promise._settlePromiseFromHandler (https://portal.breachsecurenow.com/__cypress/runner/cypress_runner.js:1489:31)\n    at Promise._settlePromise (https://portal.breachsecurenow.com/__cypress/runner/cypress_runner.js:1546:18)\n    at Promise._settlePromise0 (https://portal.breachsecurenow.com/__cypress/runner/cypress_runner.js:1591:10)\n    at Promise._settlePromises (https://portal.breachsecurenow.com/__cypress/runner/cypress_runner.js:1671:18)\n    at Promise._fulfill (https://portal.breachsecurenow.com/__cypress/runner/cypress_runner.js:1615:18)\n    at <unknown> (https://portal.breachsecurenow.com/__cypress/runner/cypress_runner.js:5420:46)",
                "diff": null
              },
              "uuid": "7cbe6670-d439-4d83-a35a-bee429ddd4ce",
              "parentUUID": "aea7bdf7-0eec-41c2-a67d-29bc37431389",
              "isHook": false,
              "skipped": false
            },
            {
              "title": "Validate all text must contains",
              "fullTitle": "UT : Manager : Company : Employee Validate all text must contains",
              "timedOut": null,
              "duration": 24052,
              "state": "failed",
              "speed": null,
              "pass": false,
              "fail": true,
              "pending": false,
              "context": null,
              "code": "EMPLOYEES.validateItems('verify-text-contains', 'UT', 'M', 'employees');",
              "err": {
                "message": "CypressError: Timed out retrying after 15000ms: `cy.wait()` timed out waiting `15000ms` for the 1st request to the route: `directorySync`. No request ever occurred.\n\nhttps://on.cypress.io/wait",
                "estack": "CypressError: Timed out retrying after 15000ms: `cy.wait()` timed out waiting `15000ms` for the 1st request to the route: `directorySync`. No request ever occurred.\n\nhttps://on.cypress.io/wait\n    at cypressErr (https://portal.breachsecurenow.com/__cypress/runner/cypress_runner.js:77680:18)\n    at Object.errByPath (https://portal.breachsecurenow.com/__cypress/runner/cypress_runner.js:77734:10)\n    at checkForXhr (https://portal.breachsecurenow.com/__cypress/runner/cypress_runner.js:138761:84)\n    at <unknown> (https://portal.breachsecurenow.com/__cypress/runner/cypress_runner.js:138787:28)\n    at tryCatcher (https://portal.breachsecurenow.com/__cypress/runner/cypress_runner.js:1777:23)\n    at Promise.attempt.Promise.try (https://portal.breachsecurenow.com/__cypress/runner/cypress_runner.js:4285:29)\n    at whenStable (https://portal.breachsecurenow.com/__cypress/runner/cypress_runner.js:147197:68)\n    at <unknown> (https://portal.breachsecurenow.com/__cypress/runner/cypress_runner.js:147138:14)\n    at tryCatcher (https://portal.breachsecurenow.com/__cypress/runner/cypress_runner.js:1777:23)\n    at Promise._settlePromiseFromHandler (https://portal.breachsecurenow.com/__cypress/runner/cypress_runner.js:1489:31)\n    at Promise._settlePromise (https://portal.breachsecurenow.com/__cypress/runner/cypress_runner.js:1546:18)\n    at Promise._settlePromise0 (https://portal.breachsecurenow.com/__cypress/runner/cypress_runner.js:1591:10)\n    at Promise._settlePromises (https://portal.breachsecurenow.com/__cypress/runner/cypress_runner.js:1671:18)\n    at Promise._fulfill (https://portal.breachsecurenow.com/__cypress/runner/cypress_runner.js:1615:18)\n    at <unknown> (https://portal.breachsecurenow.com/__cypress/runner/cypress_runner.js:5420:46)",
                "diff": null
              },
              "uuid": "892d6e71-3f0f-4ff6-bffe-cfab95316ec6",
              "parentUUID": "aea7bdf7-0eec-41c2-a67d-29bc37431389",
              "isHook": false,
              "skipped": false
            },
            {
              "title": "Validate create Manager user",
              "fullTitle": "UT : Manager : Company : Employee Validate create Manager user",
              "timedOut": null,
              "duration": 64214,
              "state": "passed",
              "speed": "slow",
              "pass": true,
              "fail": false,
              "pending": false,
              "context": null,
              "code": "EMPLOYEES.employeeUsersScenarios('create', 'MANAGER', 'employees');",
              "err": {},
              "uuid": "9ce116f2-77cd-4a3f-a99e-d3d6e795bbee",
              "parentUUID": "aea7bdf7-0eec-41c2-a67d-29bc37431389",
              "isHook": false,
              "skipped": false
            },
            {
              "title": "Validate search created Manager User",
              "fullTitle": "UT : Manager : Company : Employee Validate search created Manager User",
              "timedOut": null,
              "duration": 54844,
              "state": "failed",
              "speed": null,
              "pass": false,
              "fail": true,
              "pending": false,
              "context": null,
              "code": "EMPLOYEES.employeeUsersScenarios('search', 'MANAGER', 'employees');",
              "err": {
                "message": "AssertionError: Timed out retrying after 30000ms: expected '<td.MuiTableCell-root-215.MuiTableCell-body-217.ComponentTypes__TableCellContent-sc-nb4o94-12.eljMBW.MuiTableCell-alignLeft-222>' to contain text '350', but the text was ''",
                "estack": "AssertionError: Timed out retrying after 30000ms: expected '<td.MuiTableCell-root-215.MuiTableCell-body-217.ComponentTypes__TableCellContent-sc-nb4o94-12.eljMBW.MuiTableCell-alignLeft-222>' to contain text '350', but the text was ''\n    at Context.eval (webpack://pii-protect/./cypress/page-objects/pii-portal/my-company/employees_users.ts:971:90)\n    at getRet (https://portal.breachsecurenow.com/__cypress/runner/cypress_runner.js:121565:20)\n    at tryCatcher (https://portal.breachsecurenow.com/__cypress/runner/cypress_runner.js:1777:23)\n    at Promise.attempt.Promise.try (https://portal.breachsecurenow.com/__cypress/runner/cypress_runner.js:4285:29)\n    at Context.thenFn (https://portal.breachsecurenow.com/__cypress/runner/cypress_runner.js:121576:66)\n    at Context.then (https://portal.breachsecurenow.com/__cypress/runner/cypress_runner.js:121827:21)\n    at wrapped (https://portal.breachsecurenow.com/__cypress/runner/cypress_runner.js:141533:19)",
                "diff": "+ '350'\n"
              },
              "uuid": "0da70ee5-3f20-4047-aebf-a27109ab2c71",
              "parentUUID": "aea7bdf7-0eec-41c2-a67d-29bc37431389",
              "isHook": false,
              "skipped": false
            },
            {
              "title": "Validate update Manager User",
              "fullTitle": "UT : Manager : Company : Employee Validate update Manager User",
              "timedOut": null,
              "duration": 69781,
              "state": "failed",
              "speed": null,
              "pass": false,
              "fail": true,
              "pending": false,
              "context": null,
              "code": "EMPLOYEES.employeeUsersScenarios('update', 'MANAGER', 'employees');",
              "err": {
                "message": "AssertionError: expected 500 to equal 200",
                "estack": "AssertionError: expected 500 to equal 200\n    at Context.eval (webpack://pii-protect/./cypress/page-objects/pii-portal/my-company/employees_users.ts:1020:63)\n    at getRet (https://portal.breachsecurenow.com/__cypress/runner/cypress_runner.js:121565:20)\n    at tryCatcher (https://portal.breachsecurenow.com/__cypress/runner/cypress_runner.js:1777:23)\n    at Promise.attempt.Promise.try (https://portal.breachsecurenow.com/__cypress/runner/cypress_runner.js:4285:29)\n    at Context.thenFn (https://portal.breachsecurenow.com/__cypress/runner/cypress_runner.js:121576:66)\n    at Context.then (https://portal.breachsecurenow.com/__cypress/runner/cypress_runner.js:121827:21)",
                "diff": "- 500\n+ 200\n"
              },
              "uuid": "bd4b71a3-e30c-4254-97e8-4e4c76e305af",
              "parentUUID": "aea7bdf7-0eec-41c2-a67d-29bc37431389",
              "isHook": false,
              "skipped": false
            },
            {
              "title": "Validate delete Manager User",
              "fullTitle": "UT : Manager : Company : Employee Validate delete Manager User",
              "timedOut": null,
              "duration": 28058,
              "state": "passed",
              "speed": "slow",
              "pass": true,
              "fail": false,
              "pending": false,
              "context": null,
              "code": "EMPLOYEES.employeeUsersScenarios('delete', 'MANAGER', 'employees');",
              "err": {},
              "uuid": "5db108ad-bc28-4e5e-8f57-777b06f57e2c",
              "parentUUID": "aea7bdf7-0eec-41c2-a67d-29bc37431389",
              "isHook": false,
              "skipped": false
            },
            {
              "title": "Validate create Employee user",
              "fullTitle": "UT : Manager : Company : Employee Validate create Employee user",
              "timedOut": null,
              "duration": 70823,
              "state": "passed",
              "speed": "slow",
              "pass": true,
              "fail": false,
              "pending": false,
              "context": null,
              "code": "EMPLOYEES.employeeUsersScenarios('create', 'EMPLOYEE', 'employees');",
              "err": {},
              "uuid": "4a9f17aa-86ca-4cd3-ac0f-a02488c06461",
              "parentUUID": "aea7bdf7-0eec-41c2-a67d-29bc37431389",
              "isHook": false,
              "skipped": false
            },
            {
              "title": "Validate search created Employee User",
              "fullTitle": "UT : Manager : Company : Employee Validate search created Employee User",
              "timedOut": null,
              "duration": 54594,
              "state": "failed",
              "speed": null,
              "pass": false,
              "fail": true,
              "pending": false,
              "context": null,
              "code": "EMPLOYEES.employeeUsersScenarios('search', 'EMPLOYEE', 'employees');",
              "err": {
                "message": "AssertionError: Timed out retrying after 30000ms: expected '<td.MuiTableCell-root-215.MuiTableCell-body-217.ComponentTypes__TableCellContent-sc-nb4o94-12.eljMBW.MuiTableCell-alignLeft-222>' to contain text '350', but the text was ''",
                "estack": "AssertionError: Timed out retrying after 30000ms: expected '<td.MuiTableCell-root-215.MuiTableCell-body-217.ComponentTypes__TableCellContent-sc-nb4o94-12.eljMBW.MuiTableCell-alignLeft-222>' to contain text '350', but the text was ''\n    at Context.eval (webpack://pii-protect/./cypress/page-objects/pii-portal/my-company/employees_users.ts:971:90)\n    at getRet (https://portal.breachsecurenow.com/__cypress/runner/cypress_runner.js:121565:20)\n    at tryCatcher (https://portal.breachsecurenow.com/__cypress/runner/cypress_runner.js:1777:23)\n    at Promise.attempt.Promise.try (https://portal.breachsecurenow.com/__cypress/runner/cypress_runner.js:4285:29)\n    at Context.thenFn (https://portal.breachsecurenow.com/__cypress/runner/cypress_runner.js:121576:66)\n    at Context.then (https://portal.breachsecurenow.com/__cypress/runner/cypress_runner.js:121827:21)\n    at wrapped (https://portal.breachsecurenow.com/__cypress/runner/cypress_runner.js:141533:19)",
                "diff": "+ '350'\n"
              },
              "uuid": "0c4fa144-e01d-49a6-a8ad-9cfb9963124a",
              "parentUUID": "aea7bdf7-0eec-41c2-a67d-29bc37431389",
              "isHook": false,
              "skipped": false
            },
            {
              "title": "Validate update Employee User",
              "fullTitle": "UT : Manager : Company : Employee Validate update Employee User",
              "timedOut": null,
              "duration": 73593,
              "state": "failed",
              "speed": null,
              "pass": false,
              "fail": true,
              "pending": false,
              "context": null,
              "code": "EMPLOYEES.employeeUsersScenarios('update', 'EMPLOYEE', 'employees');",
              "err": {
                "message": "AssertionError: expected 500 to equal 200",
                "estack": "AssertionError: expected 500 to equal 200\n    at Context.eval (webpack://pii-protect/./cypress/page-objects/pii-portal/my-company/employees_users.ts:1020:63)\n    at getRet (https://portal.breachsecurenow.com/__cypress/runner/cypress_runner.js:121565:20)\n    at tryCatcher (https://portal.breachsecurenow.com/__cypress/runner/cypress_runner.js:1777:23)\n    at Promise.attempt.Promise.try (https://portal.breachsecurenow.com/__cypress/runner/cypress_runner.js:4285:29)\n    at Context.thenFn (https://portal.breachsecurenow.com/__cypress/runner/cypress_runner.js:121576:66)\n    at Context.then (https://portal.breachsecurenow.com/__cypress/runner/cypress_runner.js:121827:21)",
                "diff": "- 500\n+ 200\n"
              },
              "uuid": "5e6f4827-48e5-4111-9a77-6438f0e82315",
              "parentUUID": "aea7bdf7-0eec-41c2-a67d-29bc37431389",
              "isHook": false,
              "skipped": false
            },
            {
              "title": "Validate delete Employee User",
              "fullTitle": "UT : Manager : Company : Employee Validate delete Employee User",
              "timedOut": null,
              "duration": 29566,
              "state": "passed",
              "speed": "slow",
              "pass": true,
              "fail": false,
              "pending": false,
              "context": null,
              "code": "EMPLOYEES.employeeUsersScenarios('delete', 'EMPLOYEE', 'employees');",
              "err": {},
              "uuid": "5204a15d-97d1-4128-a371-5b2b1a0f7b8e",
              "parentUUID": "aea7bdf7-0eec-41c2-a67d-29bc37431389",
              "isHook": false,
              "skipped": false
            },
            {
              "title": "Negative - Validated search unregistered users",
              "fullTitle": "UT : Manager : Company : Employee Negative - Validated search unregistered users",
              "timedOut": null,
              "duration": 17212,
              "state": "passed",
              "speed": "slow",
              "pass": true,
              "fail": false,
              "pending": false,
              "context": null,
              "code": "EMPLOYEES.searchScenarios('unregistered-user', 'employees');",
              "err": {},
              "uuid": "c00fb514-6624-4041-9a10-06c7863ae64b",
              "parentUUID": "aea7bdf7-0eec-41c2-a67d-29bc37431389",
              "isHook": false,
              "skipped": false
            },
            {
              "title": "Validate enable send welcome message",
              "fullTitle": "UT : Manager : Company : Employee Validate enable send welcome message",
              "timedOut": null,
              "duration": 48165,
              "state": "failed",
              "speed": null,
              "pass": false,
              "fail": true,
              "pending": false,
              "context": null,
              "code": "EMPLOYEES.welcomeMessage('enable', 'employees');",
              "err": {
                "message": "AssertionError: Timed out retrying after 30000ms: Expected to find element: `[name=\"check_password\"]`, but never found it.",
                "estack": "AssertionError: Timed out retrying after 30000ms: Expected to find element: `[name=\"check_password\"]`, but never found it.\n    at employeeUsersTab.get (webpack://pii-protect/./cypress/page-objects/pii-portal/my-company/employees_users.ts:122:34)\n    at Context.eval (webpack://pii-protect/./cypress/page-objects/pii-portal/my-company/employees_users.ts:1308:33)\n    at getRet (https://portal.breachsecurenow.com/__cypress/runner/cypress_runner.js:121565:20)\n    at tryCatcher (https://portal.breachsecurenow.com/__cypress/runner/cypress_runner.js:1777:23)\n    at Promise.attempt.Promise.try (https://portal.breachsecurenow.com/__cypress/runner/cypress_runner.js:4285:29)\n    at Context.thenFn (https://portal.breachsecurenow.com/__cypress/runner/cypress_runner.js:121576:66)\n    at Context.then (https://portal.breachsecurenow.com/__cypress/runner/cypress_runner.js:121827:21)\n    at wrapped (https://portal.breachsecurenow.com/__cypress/runner/cypress_runner.js:141533:19)",
                "diff": null
              },
              "uuid": "72d9486b-dc83-4d87-b4f7-5070606b5f32",
              "parentUUID": "aea7bdf7-0eec-41c2-a67d-29bc37431389",
              "isHook": false,
              "skipped": false
            },
            {
              "title": "Validate disable send welcome message",
              "fullTitle": "UT : Manager : Company : Employee Validate disable send welcome message",
              "timedOut": null,
              "duration": 14239,
              "state": "passed",
              "speed": "slow",
              "pass": true,
              "fail": false,
              "pending": false,
              "context": null,
              "code": "EMPLOYEES.welcomeMessage('disable', 'employees');",
              "err": {},
              "uuid": "f717848a-d084-41f4-8360-a6b3abf0483a",
              "parentUUID": "aea7bdf7-0eec-41c2-a67d-29bc37431389",
              "isHook": false,
              "skipped": false
            },
            {
              "title": "Criteria: Validate `Error: A user with a matching....` must be displayed after creating a client that already exists within deleted filter",
              "fullTitle": "UT : Manager : Company : Employee Criteria: Validate `Error: A user with a matching....` must be displayed after creating a client that already exists within deleted filter",
              "timedOut": null,
              "duration": 37919,
              "state": "passed",
              "speed": "slow",
              "pass": true,
              "fail": false,
              "pending": false,
              "context": null,
              "code": "EMPLOYEES.employeeUsersScenarios('create_deleted_user', 'EMPLOYEE', 'employees');",
              "err": {},
              "uuid": "bf6c12d3-355d-41c6-83de-8bbb59f12483",
              "parentUUID": "aea7bdf7-0eec-41c2-a67d-29bc37431389",
              "isHook": false,
              "skipped": false
            },
            {
              "title": "Criteria: The banner should display until the user leaves the screen, performs another action, or the user is restored. [Removes filter]",
              "fullTitle": "UT : Manager : Company : Employee Criteria: The banner should display until the user leaves the screen, performs another action, or the user is restored. [Removes filter]",
              "timedOut": null,
              "duration": 37964,
              "state": "passed",
              "speed": "slow",
              "pass": true,
              "fail": false,
              "pending": false,
              "context": null,
              "code": "EMPLOYEES.employeeUsersScenarios('remove_filter', 'EMPLOYEE', 'employees');",
              "err": {},
              "uuid": "2983fdf1-ed90-4287-9f9d-b7decc495dd4",
              "parentUUID": "aea7bdf7-0eec-41c2-a67d-29bc37431389",
              "isHook": false,
              "skipped": false
            },
            {
              "title": "Criteria: The banner should display until the user leaves the screen, performs another action, or the user is restored. [Refresh the browser]",
              "fullTitle": "UT : Manager : Company : Employee Criteria: The banner should display until the user leaves the screen, performs another action, or the user is restored. [Refresh the browser]",
              "timedOut": null,
              "duration": 38524,
              "state": "passed",
              "speed": "slow",
              "pass": true,
              "fail": false,
              "pending": false,
              "context": null,
              "code": "EMPLOYEES.employeeUsersScenarios('reload_webpage', 'EMPLOYEE', 'employees');",
              "err": {},
              "uuid": "ffd35321-3119-46fb-b257-cf2dc2d55677",
              "parentUUID": "aea7bdf7-0eec-41c2-a67d-29bc37431389",
              "isHook": false,
              "skipped": false
            },
            {
              "title": "Criteria: The banner should display until the user leaves the screen, performs another action, or the user is restored. [Search for a user]",
              "fullTitle": "UT : Manager : Company : Employee Criteria: The banner should display until the user leaves the screen, performs another action, or the user is restored. [Search for a user]",
              "timedOut": null,
              "duration": 39478,
              "state": "passed",
              "speed": "slow",
              "pass": true,
              "fail": false,
              "pending": false,
              "context": null,
              "code": "EMPLOYEES.employeeUsersScenarios('search_user', 'EMPLOYEE', 'employees');",
              "err": {},
              "uuid": "cbca660a-6b96-4530-a6c6-4e7d8dc3149b",
              "parentUUID": "aea7bdf7-0eec-41c2-a67d-29bc37431389",
              "isHook": false,
              "skipped": false
            },
            {
              "title": "Criteria: The banner should display until the user leaves the screen, performs another action, or the user is restored. [Pagination]",
              "fullTitle": "UT : Manager : Company : Employee Criteria: The banner should display until the user leaves the screen, performs another action, or the user is restored. [Pagination]",
              "timedOut": null,
              "duration": 40023,
              "state": "passed",
              "speed": "slow",
              "pass": true,
              "fail": false,
              "pending": false,
              "context": null,
              "code": "EMPLOYEES.employeeUsersScenarios('paginate', 'EMPLOYEE', 'employees');",
              "err": {},
              "uuid": "983cdd45-3168-4087-b8db-855151cea3ad",
              "parentUUID": "aea7bdf7-0eec-41c2-a67d-29bc37431389",
              "isHook": false,
              "skipped": false
            },
            {
              "title": "Criteria: The banner should display until the user leaves the screen, performs another action, or the user is restored. [Filter any option]",
              "fullTitle": "UT : Manager : Company : Employee Criteria: The banner should display until the user leaves the screen, performs another action, or the user is restored. [Filter any option]",
              "timedOut": null,
              "duration": 38696,
              "state": "passed",
              "speed": "slow",
              "pass": true,
              "fail": false,
              "pending": false,
              "context": null,
              "code": "EMPLOYEES.employeeUsersScenarios('addFilter', 'EMPLOYEE', 'employees');",
              "err": {},
              "uuid": "276d0667-fe09-470f-b461-775dcc38eccb",
              "parentUUID": "aea7bdf7-0eec-41c2-a67d-29bc37431389",
              "isHook": false,
              "skipped": false
            },
            {
              "title": "Criteria: The banner should display until the user leaves the screen, performs another action, or the user is restored. [Download Client Report]",
              "fullTitle": "UT : Manager : Company : Employee Criteria: The banner should display until the user leaves the screen, performs another action, or the user is restored. [Download Client Report]",
              "timedOut": null,
              "duration": 39053,
              "state": "passed",
              "speed": "slow",
              "pass": true,
              "fail": false,
              "pending": false,
              "context": null,
              "code": "EMPLOYEES.employeeUsersScenarios('downloadClientReport', 'EMPLOYEE', 'employees');",
              "err": {},
              "uuid": "bd14c445-9a4c-4eb1-9ae6-6fa501e8c9b8",
              "parentUUID": "aea7bdf7-0eec-41c2-a67d-29bc37431389",
              "isHook": false,
              "skipped": false
            }
          ],
          "suites": [],
          "passes": [
            "9ce116f2-77cd-4a3f-a99e-d3d6e795bbee",
            "5db108ad-bc28-4e5e-8f57-777b06f57e2c",
            "4a9f17aa-86ca-4cd3-ac0f-a02488c06461",
            "5204a15d-97d1-4128-a371-5b2b1a0f7b8e",
            "c00fb514-6624-4041-9a10-06c7863ae64b",
            "f717848a-d084-41f4-8360-a6b3abf0483a",
            "bf6c12d3-355d-41c6-83de-8bbb59f12483",
            "2983fdf1-ed90-4287-9f9d-b7decc495dd4",
            "ffd35321-3119-46fb-b257-cf2dc2d55677",
            "cbca660a-6b96-4530-a6c6-4e7d8dc3149b",
            "983cdd45-3168-4087-b8db-855151cea3ad",
            "276d0667-fe09-470f-b461-775dcc38eccb",
            "bd14c445-9a4c-4eb1-9ae6-6fa501e8c9b8"
          ],
          "failures": [
            "7cbe6670-d439-4d83-a35a-bee429ddd4ce",
            "892d6e71-3f0f-4ff6-bffe-cfab95316ec6",
            "0da70ee5-3f20-4047-aebf-a27109ab2c71",
            "bd4b71a3-e30c-4254-97e8-4e4c76e305af",
            "0c4fa144-e01d-49a6-a8ad-9cfb9963124a",
            "5e6f4827-48e5-4111-9a77-6438f0e82315",
            "72d9486b-dc83-4d87-b4f7-5070606b5f32"
          ],
          "pending": [],
          "skipped": [],
          "duration": 868323,
          "root": false,
          "rootEmpty": false,
          "_timeout": 2000
        }
      ],
      "passes": [],
      "failures": [],
      "pending": [],
      "skipped": [],
      "duration": 0,
      "root": true,
      "rootEmpty": true,
      "_timeout": 2000
    },
    {
      "uuid": "11598c9d-1e66-4265-bf3c-29c16dddc2ef",
      "title": "",
      "fullFile": "cypress\\e2e\\unlimited-training\\manager\\my-company\\employee\\tags.cy.ts",
      "file": "cypress\\e2e\\unlimited-training\\manager\\my-company\\employee\\tags.cy.ts",
      "beforeHooks": [],
      "afterHooks": [],
      "tests": [],
      "suites": [
        {
          "uuid": "c1240a38-bef4-4863-aab2-90445ad9b008",
          "title": "UT: Manager : My Company : Tags",
          "fullFile": "",
          "file": "",
          "beforeHooks": [],
          "afterHooks": [],
          "tests": [
            {
              "title": "Default items should visible",
              "fullTitle": "UT: Manager : My Company : Tags Default items should visible",
              "timedOut": null,
              "duration": 40883,
              "state": "passed",
              "speed": "slow",
              "pass": true,
              "fail": false,
              "pending": false,
              "context": null,
              "code": "TAGS.tagsScenarios('validate-default-items', 'employees');",
              "err": {},
              "uuid": "d7197fba-5bc8-4b22-9489-cc8575df1918",
              "parentUUID": "c1240a38-bef4-4863-aab2-90445ad9b008",
              "isHook": false,
              "skipped": false
            },
            {
              "title": "Validate create new tag",
              "fullTitle": "UT: Manager : My Company : Tags Validate create new tag",
              "timedOut": null,
              "duration": 21838,
              "state": "passed",
              "speed": "slow",
              "pass": true,
              "fail": false,
              "pending": false,
              "context": null,
              "code": "TAGS.tagsScenarios('validate-create-new-tag', 'employees');",
              "err": {},
              "uuid": "75b20fc0-2733-4e4f-9817-637b00e059f8",
              "parentUUID": "c1240a38-bef4-4863-aab2-90445ad9b008",
              "isHook": false,
              "skipped": false
            },
            {
              "title": "Validate update created tag",
              "fullTitle": "UT: Manager : My Company : Tags Validate update created tag",
              "timedOut": null,
              "duration": 19775,
              "state": "passed",
              "speed": "slow",
              "pass": true,
              "fail": false,
              "pending": false,
              "context": null,
              "code": "TAGS.tagsScenarios('validate-update-created-tag', 'employees');",
              "err": {},
              "uuid": "66906914-b065-4263-a739-3d43f2b5b107",
              "parentUUID": "c1240a38-bef4-4863-aab2-90445ad9b008",
              "isHook": false,
              "skipped": false
            },
            {
              "title": "Validate delete created tag",
              "fullTitle": "UT: Manager : My Company : Tags Validate delete created tag",
              "timedOut": null,
              "duration": 21968,
              "state": "passed",
              "speed": "slow",
              "pass": true,
              "fail": false,
              "pending": false,
              "context": null,
              "code": "TAGS.tagsScenarios('validate-delete-created-tag', 'employees');",
              "err": {},
              "uuid": "55fe5aa0-4180-48e2-9c08-7890335f3ebe",
              "parentUUID": "c1240a38-bef4-4863-aab2-90445ad9b008",
              "isHook": false,
              "skipped": false
            },
            {
              "title": "OOTB - Validate duplicate Tag should not be accepted",
              "fullTitle": "UT: Manager : My Company : Tags OOTB - Validate duplicate Tag should not be accepted",
              "timedOut": null,
              "duration": 18655,
              "state": "passed",
              "speed": "slow",
              "pass": true,
              "fail": false,
              "pending": false,
              "context": null,
              "code": "TAGS.tagsScenarios('validate-existing-tags', 'employees');",
              "err": {},
              "uuid": "45da9619-0ec2-4873-b5db-96bb47b116ef",
              "parentUUID": "c1240a38-bef4-4863-aab2-90445ad9b008",
              "isHook": false,
              "skipped": false
            },
            {
              "title": "Negative - Validate cancel creating tags",
              "fullTitle": "UT: Manager : My Company : Tags Negative - Validate cancel creating tags",
              "timedOut": null,
              "duration": 16926,
              "state": "passed",
              "speed": "slow",
              "pass": true,
              "fail": false,
              "pending": false,
              "context": null,
              "code": "TAGS.tagsScenarios('cancel-create-tags', 'employees');",
              "err": {},
              "uuid": "dfa02b0c-1a45-49ba-be5b-74731bd1fdb2",
              "parentUUID": "c1240a38-bef4-4863-aab2-90445ad9b008",
              "isHook": false,
              "skipped": false
            },
            {
              "title": "Negative - Validate save button when editing tags with empty value",
              "fullTitle": "UT: Manager : My Company : Tags Negative - Validate save button when editing tags with empty value",
              "timedOut": null,
              "duration": 17243,
              "state": "passed",
              "speed": "slow",
              "pass": true,
              "fail": false,
              "pending": false,
              "context": null,
              "code": "TAGS.tagsScenarios('update-empty-value', 'employees');",
              "err": {},
              "uuid": "f69a5114-e8bb-425f-83f5-9836ac5b8c56",
              "parentUUID": "c1240a38-bef4-4863-aab2-90445ad9b008",
              "isHook": false,
              "skipped": false
            },
            {
              "title": "Negative - Validate save button is disabled when creating tags with empty value",
              "fullTitle": "UT: Manager : My Company : Tags Negative - Validate save button is disabled when creating tags with empty value",
              "timedOut": null,
              "duration": 16219,
              "state": "passed",
              "speed": "slow",
              "pass": true,
              "fail": false,
              "pending": false,
              "context": null,
              "code": "TAGS.tagsScenarios('create-empty-value', 'employees');",
              "err": {},
              "uuid": "96cee4a7-8cce-4f96-8018-f39ad43a3403",
              "parentUUID": "c1240a38-bef4-4863-aab2-90445ad9b008",
              "isHook": false,
              "skipped": false
            }
          ],
          "suites": [],
          "passes": [
            "d7197fba-5bc8-4b22-9489-cc8575df1918",
            "75b20fc0-2733-4e4f-9817-637b00e059f8",
            "66906914-b065-4263-a739-3d43f2b5b107",
            "55fe5aa0-4180-48e2-9c08-7890335f3ebe",
            "45da9619-0ec2-4873-b5db-96bb47b116ef",
            "dfa02b0c-1a45-49ba-be5b-74731bd1fdb2",
            "f69a5114-e8bb-425f-83f5-9836ac5b8c56",
            "96cee4a7-8cce-4f96-8018-f39ad43a3403"
          ],
          "failures": [],
          "pending": [],
          "skipped": [],
          "duration": 173507,
          "root": false,
          "rootEmpty": false,
          "_timeout": 2000
        }
      ],
      "passes": [],
      "failures": [],
      "pending": [],
      "skipped": [],
      "duration": 0,
      "root": true,
      "rootEmpty": true,
      "_timeout": 2000
    },
    {
      "uuid": "76cfc653-ca7d-4f13-94b2-d6eb560cdb0d",
      "title": "",
      "fullFile": "cypress\\e2e\\unlimited-training\\manager\\my-company\\training-reports\\annual.cy.ts",
      "file": "cypress\\e2e\\unlimited-training\\manager\\my-company\\training-reports\\annual.cy.ts",
      "beforeHooks": [],
      "afterHooks": [],
      "tests": [],
      "suites": [
        {
          "uuid": "2c1b8aeb-a5fb-4706-89cd-185211663477",
          "title": "UT : Manager : Company : Training Reports : Annual",
          "fullFile": "",
          "file": "",
          "beforeHooks": [],
          "afterHooks": [],
          "tests": [
            {
              "title": "Validate must exist items inside Training Reports",
              "fullTitle": "UT : Manager : Company : Training Reports : Annual Validate must exist items inside Training Reports",
              "timedOut": null,
              "duration": 30669,
              "state": "passed",
              "speed": "slow",
              "pass": true,
              "fail": false,
              "pending": false,
              "context": null,
              "code": "TRAINING_REPORTS.annual('validate-items', '');",
              "err": {},
              "uuid": "9d6937f9-456a-4a5f-8fc6-1279049f51eb",
              "parentUUID": "2c1b8aeb-a5fb-4706-89cd-185211663477",
              "isHook": false,
              "skipped": false
            },
            {
              "title": "Validate viewing certificates done by all users in 2023 Cybersecurity Training",
              "fullTitle": "UT : Manager : Company : Training Reports : Annual Validate viewing certificates done by all users in 2023 Cybersecurity Training",
              "timedOut": null,
              "duration": 72318,
              "state": "passed",
              "speed": "slow",
              "pass": true,
              "fail": false,
              "pending": false,
              "context": null,
              "code": "TRAINING_REPORTS.annual('view-all-certificates', '2023 Cybersecurity Training');",
              "err": {},
              "uuid": "ecfbb498-57b5-4a80-9a9c-7d9e06099bef",
              "parentUUID": "2c1b8aeb-a5fb-4706-89cd-185211663477",
              "isHook": false,
              "skipped": false
            },
            {
              "title": "Validate viewing certificates done by all users in 2023 Cyber Manager Training",
              "fullTitle": "UT : Manager : Company : Training Reports : Annual Validate viewing certificates done by all users in 2023 Cyber Manager Training",
              "timedOut": null,
              "duration": 54625,
              "state": "passed",
              "speed": "slow",
              "pass": true,
              "fail": false,
              "pending": false,
              "context": null,
              "code": "TRAINING_REPORTS.annual('view-all-certificates', '2023 Cyber Manager Training');",
              "err": {},
              "uuid": "91e57133-c87a-4391-b310-a95dba575176",
              "parentUUID": "2c1b8aeb-a5fb-4706-89cd-185211663477",
              "isHook": false,
              "skipped": false
            },
            {
              "title": "Validate viewing certificates done by all users in 2022 Cybersecurity Training",
              "fullTitle": "UT : Manager : Company : Training Reports : Annual Validate viewing certificates done by all users in 2022 Cybersecurity Training",
              "timedOut": null,
              "duration": 73634,
              "state": "passed",
              "speed": "slow",
              "pass": true,
              "fail": false,
              "pending": false,
              "context": null,
              "code": "TRAINING_REPORTS.annual('view-all-certificates', '2022 Cybersecurity Training');",
              "err": {},
              "uuid": "a7f3fbd6-2e6a-4b77-9714-49386a41991a",
              "parentUUID": "2c1b8aeb-a5fb-4706-89cd-185211663477",
              "isHook": false,
              "skipped": false
            },
            {
              "title": "Validate downloading certificates done by all users in 2023 Cybersecurity Training",
              "fullTitle": "UT : Manager : Company : Training Reports : Annual Validate downloading certificates done by all users in 2023 Cybersecurity Training",
              "timedOut": null,
              "duration": 36638,
              "state": "failed",
              "speed": null,
              "pass": false,
              "fail": true,
              "pending": false,
              "context": null,
              "code": "TRAINING_REPORTS.annual('download-all-certificates', '2023 Cybersecurity Training');",
              "err": {
                "message": "AssertionError: expected '\\n\\nCERTIFICATE\\nOF ACHIEVEMENT\\nPROUDLY PRESENTED TO\\nUT manager admin Automation\\nFOR SUCCESSFUL COMPLETION OF THE COURSE:\\n2023 Cybersecurity Training\\nCOMPLETION GRADE: 100%\\nCOMPLETED ON: 2023-01-07\\nThis certificate was awarded by:\\nApril Partner Prod 7\\non behalf of:\\nUT Existing Client' to include 'UT Existing Client\\n'",
                "estack": "AssertionError: expected '\\n\\nCERTIFICATE\\nOF ACHIEVEMENT\\nPROUDLY PRESENTED TO\\nUT manager admin Automation\\nFOR SUCCESSFUL COMPLETION OF THE COURSE:\\n2023 Cybersecurity Training\\nCOMPLETION GRADE: 100%\\nCOMPLETED ON: 2023-01-07\\nThis certificate was awarded by:\\nApril Partner Prod 7\\non behalf of:\\nUT Existing Client' to include 'UT Existing Client\\n'\n    at Context.eval (webpack://pii-protect/./cypress/page-objects/pii-portal/my-company/training_reports.ts:172:67)\n    at getRet (https://portal.breachsecurenow.com/__cypress/runner/cypress_runner.js:121565:20)\n    at tryCatcher (https://portal.breachsecurenow.com/__cypress/runner/cypress_runner.js:1777:23)\n    at Promise.attempt.Promise.try (https://portal.breachsecurenow.com/__cypress/runner/cypress_runner.js:4285:29)\n    at Context.thenFn (https://portal.breachsecurenow.com/__cypress/runner/cypress_runner.js:121576:66)\n    at Context.then (https://portal.breachsecurenow.com/__cypress/runner/cypress_runner.js:121827:21)",
                "diff": null
              },
              "uuid": "6006514a-64ea-4d75-a938-5d24e9b906ee",
              "parentUUID": "2c1b8aeb-a5fb-4706-89cd-185211663477",
              "isHook": false,
              "skipped": false
            },
            {
              "title": "Validate downloading certificates done by all users in 2023 Cyber Manager Training",
              "fullTitle": "UT : Manager : Company : Training Reports : Annual Validate downloading certificates done by all users in 2023 Cyber Manager Training",
              "timedOut": null,
              "duration": 35859,
              "state": "failed",
              "speed": null,
              "pass": false,
              "fail": true,
              "pending": false,
              "context": null,
              "code": "TRAINING_REPORTS.annual('download-all-certificates', '2023 Cyber Manager Training');",
              "err": {
                "message": "AssertionError: expected '\\n\\nCERTIFICATE\\nOF ACHIEVEMENT\\nPROUDLY PRESENTED TO\\nUT manager admin Automation\\nFOR SUCCESSFUL COMPLETION OF THE COURSE:\\n2023 Cybersecurity Training\\nCOMPLETION GRADE: 100%\\nCOMPLETED ON: 2023-01-07\\nThis certificate was awarded by:\\nApril Partner Prod 7\\non behalf of:\\nUT Existing Client' to include '2023 Cyber Manager Training\\n'",
                "estack": "AssertionError: expected '\\n\\nCERTIFICATE\\nOF ACHIEVEMENT\\nPROUDLY PRESENTED TO\\nUT manager admin Automation\\nFOR SUCCESSFUL COMPLETION OF THE COURSE:\\n2023 Cybersecurity Training\\nCOMPLETION GRADE: 100%\\nCOMPLETED ON: 2023-01-07\\nThis certificate was awarded by:\\nApril Partner Prod 7\\non behalf of:\\nUT Existing Client' to include '2023 Cyber Manager Training\\n'\n    at Context.eval (webpack://pii-protect/./cypress/page-objects/pii-portal/my-company/training_reports.ts:162:72)\n    at getRet (https://portal.breachsecurenow.com/__cypress/runner/cypress_runner.js:121565:20)\n    at tryCatcher (https://portal.breachsecurenow.com/__cypress/runner/cypress_runner.js:1777:23)\n    at Promise.attempt.Promise.try (https://portal.breachsecurenow.com/__cypress/runner/cypress_runner.js:4285:29)\n    at Context.thenFn (https://portal.breachsecurenow.com/__cypress/runner/cypress_runner.js:121576:66)\n    at Context.then (https://portal.breachsecurenow.com/__cypress/runner/cypress_runner.js:121827:21)",
                "diff": null
              },
              "uuid": "ea28f39a-7331-4158-89ec-070984c98c91",
              "parentUUID": "2c1b8aeb-a5fb-4706-89cd-185211663477",
              "isHook": false,
              "skipped": false
            },
            {
              "title": "Validate downloading certificates done by all users in 2022 Cybersecurity Training",
              "fullTitle": "UT : Manager : Company : Training Reports : Annual Validate downloading certificates done by all users in 2022 Cybersecurity Training",
              "timedOut": null,
              "duration": 36411,
              "state": "failed",
              "speed": null,
              "pass": false,
              "fail": true,
              "pending": false,
              "context": null,
              "code": "TRAINING_REPORTS.annual('download-all-certificates', '2022 Cybersecurity Training');",
              "err": {
                "message": "AssertionError: expected '\\n\\nCERTIFICATE\\nOF ACHIEVEMENT\\nPROUDLY PRESENTED TO\\nUT employee Automation\\nFOR SUCCESSFUL COMPLETION OF THE COURSE:\\n2022 Cybersecurity Training\\nCOMPLETION GRADE: 100%\\nCOMPLETED ON: 2022-11-03\\nThis certificate was awarded by:\\nApril Partner Prod 7\\non behalf of:\\nUT Existing Client' to include 'UT Existing Client\\n'",
                "estack": "AssertionError: expected '\\n\\nCERTIFICATE\\nOF ACHIEVEMENT\\nPROUDLY PRESENTED TO\\nUT employee Automation\\nFOR SUCCESSFUL COMPLETION OF THE COURSE:\\n2022 Cybersecurity Training\\nCOMPLETION GRADE: 100%\\nCOMPLETED ON: 2022-11-03\\nThis certificate was awarded by:\\nApril Partner Prod 7\\non behalf of:\\nUT Existing Client' to include 'UT Existing Client\\n'\n    at Context.eval (webpack://pii-protect/./cypress/page-objects/pii-portal/my-company/training_reports.ts:172:67)\n    at getRet (https://portal.breachsecurenow.com/__cypress/runner/cypress_runner.js:121565:20)\n    at tryCatcher (https://portal.breachsecurenow.com/__cypress/runner/cypress_runner.js:1777:23)\n    at Promise.attempt.Promise.try (https://portal.breachsecurenow.com/__cypress/runner/cypress_runner.js:4285:29)\n    at Context.thenFn (https://portal.breachsecurenow.com/__cypress/runner/cypress_runner.js:121576:66)\n    at Context.then (https://portal.breachsecurenow.com/__cypress/runner/cypress_runner.js:121827:21)",
                "diff": null
              },
              "uuid": "6d94e73e-0a64-4857-94df-c615cf46561d",
              "parentUUID": "2c1b8aeb-a5fb-4706-89cd-185211663477",
              "isHook": false,
              "skipped": false
            },
            {
              "title": "Validate downloading Selected Training Report",
              "fullTitle": "UT : Manager : Company : Training Reports : Annual Validate downloading Selected Training Report",
              "timedOut": null,
              "duration": 13881,
              "state": "passed",
              "speed": "slow",
              "pass": true,
              "fail": false,
              "pending": false,
              "context": null,
              "code": "TRAINING_REPORTS.annual('download-selected-training-report', '');",
              "err": {},
              "uuid": "8399ed7f-da9f-4b86-b9a1-293a7d850974",
              "parentUUID": "2c1b8aeb-a5fb-4706-89cd-185211663477",
              "isHook": false,
              "skipped": false
            },
            {
              "title": "Validate searching existing client in Annual",
              "fullTitle": "UT : Manager : Company : Training Reports : Annual Validate searching existing client in Annual",
              "timedOut": null,
              "duration": 26021,
              "state": "passed",
              "speed": "slow",
              "pass": true,
              "fail": false,
              "pending": false,
              "context": null,
              "code": "TRAINING_REPORTS.annual('search-existing-user', '');",
              "err": {},
              "uuid": "47ee3f00-3aa0-4219-bbef-974966a36c31",
              "parentUUID": "2c1b8aeb-a5fb-4706-89cd-185211663477",
              "isHook": false,
              "skipped": false
            },
            {
              "title": "Negative: Validate searching non existing client in Annual",
              "fullTitle": "UT : Manager : Company : Training Reports : Annual Negative: Validate searching non existing client in Annual",
              "timedOut": null,
              "duration": 21388,
              "state": "passed",
              "speed": "slow",
              "pass": true,
              "fail": false,
              "pending": false,
              "context": null,
              "code": "TRAINING_REPORTS.annual('search-non-existing-user', '');",
              "err": {},
              "uuid": "6b46ab81-d049-4491-8fa2-ff4af2551f25",
              "parentUUID": "2c1b8aeb-a5fb-4706-89cd-185211663477",
              "isHook": false,
              "skipped": false
            }
          ],
          "suites": [],
          "passes": [
            "9d6937f9-456a-4a5f-8fc6-1279049f51eb",
            "ecfbb498-57b5-4a80-9a9c-7d9e06099bef",
            "91e57133-c87a-4391-b310-a95dba575176",
            "a7f3fbd6-2e6a-4b77-9714-49386a41991a",
            "8399ed7f-da9f-4b86-b9a1-293a7d850974",
            "47ee3f00-3aa0-4219-bbef-974966a36c31",
            "6b46ab81-d049-4491-8fa2-ff4af2551f25"
          ],
          "failures": [
            "6006514a-64ea-4d75-a938-5d24e9b906ee",
            "ea28f39a-7331-4158-89ec-070984c98c91",
            "6d94e73e-0a64-4857-94df-c615cf46561d"
          ],
          "pending": [],
          "skipped": [],
          "duration": 401444,
          "root": false,
          "rootEmpty": false,
          "_timeout": 2000
        }
      ],
      "passes": [],
      "failures": [],
      "pending": [],
      "skipped": [],
      "duration": 0,
      "root": true,
      "rootEmpty": true,
      "_timeout": 2000
    }
  ],
  "meta": {
    "mocha": {
      "version": "7.2.0"
    },
    "mochawesome": {
      "options": {
        "quiet": false,
        "reportFilename": "mochawesome",
        "saveHtml": false,
        "saveJson": true,
        "consoleReporter": "spec",
        "useInlineDiffs": false,
        "code": true
      },
      "version": "7.1.3"
    },
    "marge": {
      "options": {
        "id": "default",
        "reportDir": "cypress/reports/mocha",
        "quite": true,
        "overwrite": false,
        "html": false,
        "json": true
      },
      "version": "6.2.0"
    }
  }
}